questions_gen/__init__.py
questions_gen/cli/__init__.py
questions_gen/cli/main_cli.py
questions_gen/core/__init__.py
questions_gen/core/config.py
questions_gen/core/trainer.py
questions_gen/data/__init__.py
questions_gen/data/data_preparer.py
questions_gen/utils/__init__.py
questions_gen/utils/hf_utils.py
questions_gen/utils/ollama_manager.py
questions_gen/validation/__init__.py
questions_gen/validation/batch_validator.py
questions_gen/validation/model_validator.py
questions_gen/validation/quality_evaluator.py
questions_gen-0.1.1.dist-info/licenses/LICENSE
questions_gen-0.1.1.dist-info/METADATA
questions_gen-0.1.1.dist-info/WHEEL
questions_gen-0.1.1.dist-info/entry_points.txt
questions_gen-0.1.1.dist-info/top_level.txt
questions_gen-0.1.1.dist-info/RECORD
