Metadata-Version: 2.4
Name: questions-gen
Version: 0.1.1
Summary: AI-Powered Mathematical Competition Problem Generation Package
Author-email: Xingqiang Chen <xingqiangchen@turingai.cc>
Maintainer-email: Xingqiang Chen <xingqiangchen@turingai.cc>
License-Expression: Apache-2.0
Project-URL: Homepage, https://github.com/xingqiang/questions-gen
Project-URL: Repository, https://github.com/xingqiang/questions-gen
Project-URL: Documentation, https://github.com/xingqiang/questions-gen/wiki
Project-URL: Bug Reports, https://github.com/xingqiang/questions-gen/issues
Project-URL: Models, https://huggingface.co/xingqiang
Keywords: artificial intelligence,machine learning,natural language processing,mathematical problem generation,education technology,competition mathematics,language model,fine-tuning,reinforcement learning,knowledge distillation
Classifier: Development Status :: 4 - Beta
Classifier: Intended Audience :: Education
Classifier: Intended Audience :: Science/Research
Classifier: Operating System :: OS Independent
Classifier: Programming Language :: Python :: 3
Classifier: Programming Language :: Python :: 3.8
Classifier: Programming Language :: Python :: 3.9
Classifier: Programming Language :: Python :: 3.10
Classifier: Programming Language :: Python :: 3.11
Classifier: Topic :: Scientific/Engineering :: Artificial Intelligence
Classifier: Topic :: Education
Classifier: Topic :: Text Processing :: Linguistic
Requires-Python: >=3.8
License-File: LICENSE
Requires-Dist: torch>=2.0.0
Requires-Dist: transformers>=4.35.0
Requires-Dist: unsloth[colab-new]>=2024.1
Requires-Dist: datasets>=2.14.0
Requires-Dist: trl>=0.7.0
Requires-Dist: scikit-learn>=1.3.0
Requires-Dist: numpy>=1.24.0
Requires-Dist: pandas>=2.0.0
Requires-Dist: openai>=1.0.0
Requires-Dist: huggingface_hub>=0.17.0
Requires-Dist: accelerate>=0.24.0
Requires-Dist: bitsandbytes>=0.41.0
Requires-Dist: peft>=0.6.0
Requires-Dist: xformers>=0.0.22
Provides-Extra: dev
Requires-Dist: pytest>=7.0.0; extra == "dev"
Requires-Dist: pytest-cov>=4.0.0; extra == "dev"
Requires-Dist: black>=22.0.0; extra == "dev"
Requires-Dist: flake8>=4.0.0; extra == "dev"
Requires-Dist: isort>=5.0.0; extra == "dev"
Requires-Dist: mypy>=0.950; extra == "dev"
Provides-Extra: full
Requires-Dist: jupyter>=1.0.0; extra == "full"
Requires-Dist: matplotlib>=3.5.0; extra == "full"
Requires-Dist: seaborn>=0.11.0; extra == "full"
Requires-Dist: plotly>=5.0.0; extra == "full"
Dynamic: license-file
